nowem/__init__.py
nowem/aiorequests.py
nowem/client.py
nowem/exception.py
nowem/logger.py
nowem/playerprefs.py
nowem/secret.py
nowem-0.0.9.dist-info/METADATA
nowem-0.0.9.dist-info/WHEEL
nowem-0.0.9.dist-info/top_level.txt
nowem-0.0.9.dist-info/RECORD
