Metadata-Version: 2.1
Name: nowem
Version: 0.0.9
Summary: API wrapper for princess connect re:dive(tw server)
Home-page: https://github.com/TWT233/nowem
Author: TWT233
Author-email: TWT2333@outlook.com
License: UNKNOWN
Platform: UNKNOWN
Classifier: Programming Language :: Python :: 3
Classifier: License :: OSI Approved :: MIT License
Classifier: Operating System :: OS Independent
Requires-Python: >=3.6
Requires-Dist: requests (==2.25.1)
Requires-Dist: msgpack (>=1.0.1)
Requires-Dist: pycryptodomex (>=3.9.9)
